[
    {
        "scene_id": 9,
        "image_id": 0,
        "category_id": 14,
        "R": [
            [
                0.8869481759489896,
                -0.1225364735873197,
                -0.4453175786127753
            ],
            [
                0.461789301605613,
                0.2531776803731752,
                0.8500892324241373
            ],
            [
                0.008577534806776234,
                -0.9596279877127613,
                0.281141514357087
            ]
        ],
        "t": [
            -37.799701626782905,
            -16.50077286396322,
            1715.789286007446
        ]
    }
]