[
    {
        "scene_id": 10,
        "image_id": 5,
        "category_id": 1,
        "R": [
            [
                0.31790399775835,
                0.8720834752324866,
                -0.3720315497418569
            ],
            [
                0.8987488143590802,
                -0.4021544621539968,
                -0.17470673510831364
            ],
            [
                -0.3019729610577334,
                -0.278822932324246,
                -0.9116304348848416
            ]
        ],
        "t": [
            3.0318551545066157,
            260.72489015038957,
            1951.5083463246856
        ]
    }
]